ducpy/__init__.py
ducpy/_version.py
ducpy/parse.py
ducpy/serialize.py
ducpy/Duc/ANGULAR_UNITS_FORMAT.py
ducpy/Duc/AXIS.py
ducpy/Duc/AlternateUnits.py
ducpy/Duc/AngularUnitSystem.py
ducpy/Duc/BEZIER_MIRRORING.py
ducpy/Duc/BLENDING.py
ducpy/Duc/BLOCK_ATTACHMENT.py
ducpy/Duc/BOOLEAN_OPERATION.py
ducpy/Duc/BoundElement.py
ducpy/Duc/COLUMN_TYPE.py
ducpy/Duc/Checkpoint.py
ducpy/Duc/ColumnLayout.py
ducpy/Duc/CustomHatchPattern.py
ducpy/Duc/DATUM_BRACKET_STYLE.py
ducpy/Duc/DATUM_TARGET_TYPE.py
ducpy/Duc/DECIMAL_SEPARATOR.py
ducpy/Duc/DIMENSION_FIT_RULE.py
ducpy/Duc/DIMENSION_TEXT_PLACEMENT.py
ducpy/Duc/DIMENSION_TYPE.py
ducpy/Duc/DIMENSION_UNITS_FORMAT.py
ducpy/Duc/DatumReference.py
ducpy/Duc/Delta.py
ducpy/Duc/DictionaryEntry.py
ducpy/Duc/DimensionBaselineData.py
ducpy/Duc/DimensionBindings.py
ducpy/Duc/DimensionContinueData.py
ducpy/Duc/DimensionDefinitionPoints.py
ducpy/Duc/DimensionExtLineStyle.py
ducpy/Duc/DimensionFitStyle.py
ducpy/Duc/DimensionLineStyle.py
ducpy/Duc/DimensionSymbolStyle.py
ducpy/Duc/DimensionToleranceStyle.py
ducpy/Duc/DimensionValidationRules.py
ducpy/Duc/DucArrowElement.py
ducpy/Duc/DucBlock.py
ducpy/Duc/DucBlockAttributeDefinition.py
ducpy/Duc/DucBlockAttributeDefinitionEntry.py
ducpy/Duc/DucBlockCollection.py
ducpy/Duc/DucBlockCollectionEntry.py
ducpy/Duc/DucBlockDuplicationArray.py
ducpy/Duc/DucBlockInstance.py
ducpy/Duc/DucBlockInstanceElement.py
ducpy/Duc/DucBlockMetadata.py
ducpy/Duc/DucCommonStyle.py
ducpy/Duc/DucDimensionElement.py
ducpy/Duc/DucDimensionStyle.py
ducpy/Duc/DucDocElement.py
ducpy/Duc/DucDocStyle.py
ducpy/Duc/DucEllipseElement.py
ducpy/Duc/DucEmbeddableElement.py
ducpy/Duc/DucExternalFileData.py
ducpy/Duc/DucExternalFileEntry.py
ducpy/Duc/DucFeatureControlFrameElement.py
ducpy/Duc/DucFeatureControlFrameStyle.py
ducpy/Duc/DucFrameElement.py
ducpy/Duc/DucFreeDrawElement.py
ducpy/Duc/DucFreeDrawEnds.py
ducpy/Duc/DucGlobalState.py
ducpy/Duc/DucGroup.py
ducpy/Duc/DucHatchStyle.py
ducpy/Duc/DucHead.py
ducpy/Duc/DucImageElement.py
ducpy-2.3.0.dist-info/licenses/LICENSE
ducpy-2.3.0.dist-info/METADATA
ducpy-2.3.0.dist-info/WHEEL
ducpy-2.3.0.dist-info/top_level.txt
ducpy-2.3.0.dist-info/RECORD
