Metadata-Version: 2.4
Name: ducpy
Version: 2.3.0
Summary: The library for the Duc 2D CAD file format
Author: Jorge Soares
Author-email: Ducflair <support@ducflair.com>
License: MIT
Project-URL: Homepage, https://duc.ducflair.com
Project-URL: Source, https://github.com/ducflair/duc/tree/main/packages/ducpy
Project-URL: Documentation, https://python.duc.ducflair.com
Classifier: License :: OSI Approved :: MIT License
Requires-Python: >=3.10
License-File: LICENSE
Requires-Dist: flatbuffers>=25.2.10
Requires-Dist: nanoid>=2.0.0
Dynamic: license-file
